setup.py
oscheck/__init__.py
oscheck/exceptions.py
oscheck.egg-info/PKG-INFO
oscheck.egg-info/SOURCES.txt
oscheck.egg-info/dependency_links.txt
oscheck.egg-info/top_level.txt
tests/__init__.py
tests/main.py